aidb/__init__.py
aidb/launch.py
aidb/config/__init__.py
aidb/config/config.py
aidb/config/config_types.py
aidb/engine/__init__.py
aidb/engine/approx_aggregate_engine.py
aidb/engine/base_engine.py
aidb/engine/engine.py
aidb/engine/full_scan_engine.py
aidb/engine/limit_engine.py
aidb/engine/non_select_query_engine.py
aidb/engine/tasti_engine.py
aidb/estimator/__init__.py
aidb/estimator/estimator.py
aidb/inference/__init__.py
aidb/inference/bound_inference_service.py
aidb/inference/cached_inference_service.py
aidb/inference/http_inference_service.py
aidb/inference/inference_service.py
aidb/inference/examples/__init__.py
aidb/inference/examples/detectron_local_ocr.py
aidb/inference/examples/google_inference_service.py
aidb/inference/examples/huggingface_inference_service.py
aidb/inference/examples/openai_inference_service.py
aidb/inference/examples/pytorch_local_detection.py
aidb/query/__init__.py
aidb/query/query.py
aidb/query/utils.py
aidb/samplers/__init__.py
aidb/samplers/sampler.py
aidb/utils/__init__.py
aidb/utils/asyncio.py
aidb/utils/constants.py
aidb/utils/db.py
aidb/utils/logger.py
aidb/utils/perf_utils.py
aidb/utils/type_conversion.py
aidb/vector_database/__init__.py
aidb/vector_database/chroma_vector_database.py
aidb/vector_database/faiss_vector_database.py
aidb/vector_database/tasti.py
aidb/vector_database/vector_database.py
aidb/vector_database/vector_database_config.py
aidb/vector_database/weaviate_vector_database.py
aidb_utilities/__init__.py
aidb_utilities/aidb_setup/__init__.py
aidb_utilities/aidb_setup/aidb_factory.py
aidb_utilities/blob_store/__init__.py
aidb_utilities/blob_store/aws_s3_storage.py
aidb_utilities/blob_store/blob_store.py
aidb_utilities/blob_store/local_storage.py
aidb_utilities/blob_store/utils.py
aidb_utilities/command_line_setup/__init__.py
aidb_utilities/command_line_setup/command_line_setup.py
aidb_utilities/db_setup/__init__.py
aidb_utilities/db_setup/blob_table.py
aidb_utilities/db_setup/create_tables.py
ai_db-0.0.2.dist-info/LICENSE
ai_db-0.0.2.dist-info/METADATA
ai_db-0.0.2.dist-info/WHEEL
ai_db-0.0.2.dist-info/top_level.txt
ai_db-0.0.2.dist-info/RECORD
