Metadata-Version: 2.1
Name: ai-db
Version: 0.0.2
Summary: Analyze your unstructured data
Home-page: UNKNOWN
Author: Daniel Kang
Author-email: daniel.d.kang@gmail.com
License: UNKNOWN
Platform: UNKNOWN
Classifier: Intended Audience :: Developers
Classifier: License :: OSI Approved :: Apache Software License
Classifier: Operating System :: OS Independent
Classifier: Programming Language :: SQL
Classifier: Programming Language :: Python :: 3 :: Only
Requires-Python: >=3.9
License-File: LICENSE
Requires-Dist: aiomysql ==0.2.0
Requires-Dist: aiosqlite ==0.19.0
Requires-Dist: annotated-types ==0.5.0
Requires-Dist: anyio ==3.7.1
Requires-Dist: asyncpg ==0.28.0
Requires-Dist: boto3 ==1.28.63
Requires-Dist: certifi ==2023.7.22
Requires-Dist: charset-normalizer ==3.2.0
Requires-Dist: chromadb ==0.4.11
Requires-Dist: click ==8.1.7
Requires-Dist: exceptiongroup ==1.1.3
Requires-Dist: faiss-cpu ==1.7.4
Requires-Dist: fastapi ==0.99.1
Requires-Dist: flatten-json ==0.1.13
Requires-Dist: gdown ==4.7.1
Requires-Dist: greenlet ==2.0.2
Requires-Dist: h11 ==0.14.0
Requires-Dist: idna ==3.4
Requires-Dist: iniconfig ==2.0.0
Requires-Dist: nest-asyncio ==1.5.7
Requires-Dist: networkx ==3.1
Requires-Dist: numba ==0.58.0
Requires-Dist: numpy ==1.24.4
Requires-Dist: packaging ==23.1
Requires-Dist: pandas ==2.0.3
Requires-Dist: Pillow ==10.1.0
Requires-Dist: pluggy ==1.3.0
Requires-Dist: pydantic ==1.10.12
Requires-Dist: PyMySQL ==1.1.0
Requires-Dist: pytest ==7.4.2
Requires-Dist: python-dateutil ==2.8.2
Requires-Dist: pytz ==2023.3.post1
Requires-Dist: PyYAML ==6.0.1
Requires-Dist: requests ==2.31.0
Requires-Dist: scipy ==1.10.1
Requires-Dist: six ==1.16.0
Requires-Dist: sniffio ==1.3.0
Requires-Dist: SQLAlchemy ==1.4.39
Requires-Dist: SQLAlchemy-Utils ==0.41.1
Requires-Dist: sqlglot-aidb ==0.0.5
Requires-Dist: starlette ==0.27.0
Requires-Dist: statsmodels ==0.14.0
Requires-Dist: sympy ==1.11.1
Requires-Dist: tomli ==2.0.1
Requires-Dist: tqdm ==4.66.1
Requires-Dist: typing-extensions ==4.7.1
Requires-Dist: tzdata ==2023.3
Requires-Dist: urllib3 ==1.26.17
Requires-Dist: uvicorn ==0.23.2
Requires-Dist: weaviate-client ==3.24.1
